{
  "pieces":[
    {
      "piece":"White King",
      "position":60
    },
    {
      "piece":"Black King",
      "position":4
    },
    {
      "piece":"White Queen",
      "position":59
    },
    {
      "piece":"Black Queen",
      "position":3
    },
    {
      "piece":"White King Bishop",
      "position":61
    },
    {
      "piece":"Black King Bishop",
      "position":5
    },
    {
      "piece":"White Queen Bishop",
      "position":58
    },
    {
      "piece":"Black Queen Bishop",
      "position":2
    },
    {
      "piece":"White King Knight",
      "position":62
    },
    {
      "piece":"Black King Knight",
      "position":6
    },
    {
      "piece":"White Queen Knight",
      "position":57
    },
    {
      "piece":"Black Queen Knight",
      "position":1
    },
    {
      "piece":"White King Rook",
      "position":63
    },
    {
      "piece":"Black King Rook",
      "position":7
    },
    {
      "piece":"White Queen Rook",
      "position":56
    },
    {
      "piece":"Black Queen Rook",
      "position":0
    },
    {
      "piece":"White Pawn",
      "position":48
    },
    {
      "piece":"White Pawn",
      "position":49
    },
    {
      "piece":"White Pawn",
      "position":50
    },
    {
      "piece":"White Pawn",
      "position":51
    },
    {
      "piece":"White Pawn",
      "position":52
    },
    {
      "piece":"White Pawn",
      "position":53
    },
    {
      "piece":"White Pawn",
      "position":54
    },
    {
      "piece":"White Pawn",
      "position":55
    },
    {
      "piece":"Black Pawn",
      "position":8
    },
    {
      "piece":"Black Pawn",
      "position":9
    },
    {
      "piece":"Black Pawn",
      "position":10
    },
    {
      "piece":"Black Pawn",
      "position":11
    },
    {
      "piece":"Black Pawn",
      "position":12
    },
    {
      "piece":"Black Pawn",
      "position":13
    },
    {
      "piece":"Black Pawn",
      "position":14
    },
    {
      "piece":"Black Pawn",
      "position":15
    }
  ]
}
